{
  "businesses": [
      {
          "id": "c6kgy8xloCSocUii0p1rKw",
          "alias": "playalinda-beach-titusville",
          "name": "Playalinda Beach",
          "image_url": "https://s3-media2.fl.yelpcdn.com/bphoto/9K3DjsXONl5kBDEzR9MNdg/o.jpg",
          "is_closed": false,
          "url": "https://www.yelp.com/biz/playalinda-beach-titusville?adjust_creative=Yv4LCvsm1QJ6GtOp27fQ_w&utm_campaign=yelp_api_v3&utm_medium=api_v3_business_search&utm_source=Yv4LCvsm1QJ6GtOp27fQ_w",
          "review_count": 50,
          "categories": [
              {
                  "alias": "beaches",
                  "title": "Beaches"
              }
          ],
          "rating": 4.5,
          "coordinates": {
              "latitude": 28.78752,
              "longitude": -80.754426
          },
          "transactions": [],
          "location": {
              "address1": "Canaveral National Seashore",
              "address2": "",
              "address3": "SR 402",
              "city": "Titusville",
              "zip_code": "32796",
              "country": "US",
              "state": "FL",
              "display_address": [
                  "Canaveral National Seashore",
                  "SR 402",
                  "Titusville, FL 32796"
              ]
          },
          "phone": "",
          "display_phone": "",
          "distance": 66963.18620889462
      },
      {
          "id": "jt4hU0DmJedSeXv_K1vVIA",
          "alias": "new-smyrna-beach-city-of-new-smyrna-beach-2",
          "name": "New Smyrna Beach City of",
          "image_url": "https://s3-media4.fl.yelpcdn.com/bphoto/PolgDclvHqPufMpQWRK1Nw/o.jpg",
          "is_closed": false,
          "url": "https://www.yelp.com/biz/new-smyrna-beach-city-of-new-smyrna-beach-2?adjust_creative=Yv4LCvsm1QJ6GtOp27fQ_w&utm_campaign=yelp_api_v3&utm_medium=api_v3_business_search&utm_source=Yv4LCvsm1QJ6GtOp27fQ_w",
          "review_count": 34,
          "categories": [
              {
                  "alias": "beaches",
                  "title": "Beaches"
              }
          ],
          "rating": 4.5,
          "coordinates": {
              "latitude": 29.0374276,
              "longitude": -80.9001016
          },
          "transactions": [],
          "location": {
              "address1": "308 Columbus Ave",
              "address2": "",
              "address3": "",
              "city": "New Smyrna Beach",
              "zip_code": "32169",
              "country": "US",
              "state": "FL",
              "display_address": [
                  "308 Columbus Ave",
                  "New Smyrna Beach, FL 32169"
              ]
          },
          "phone": "+13864242216",
          "display_phone": "(386) 424-2216",
          "distance": 72544.65458708665
      },
      {
          "id": "J63q7OLb3IdViF9f97QGLg",
          "alias": "cocoa-beach-cocoa-beach",
          "name": "Cocoa Beach",
          "image_url": "https://s3-media4.fl.yelpcdn.com/bphoto/s8acoP6iyUh6DgxIVvjuJg/o.jpg",
          "is_closed": false,
          "url": "https://www.yelp.com/biz/cocoa-beach-cocoa-beach?adjust_creative=Yv4LCvsm1QJ6GtOp27fQ_w&utm_campaign=yelp_api_v3&utm_medium=api_v3_business_search&utm_source=Yv4LCvsm1QJ6GtOp27fQ_w",
          "review_count": 130,
          "categories": [
              {
                  "alias": "beaches",
                  "title": "Beaches"
              }
          ],
          "rating": 4.0,
          "coordinates": {
              "latitude": 28.2975283554243,
              "longitude": -80.6059430379736
          },
          "transactions": [],
          "location": {
              "address1": "1033 S Atlantic Ave",
              "address2": "",
              "address3": "",
              "city": "Cocoa Beach",
              "zip_code": "32931",
              "country": "US",
              "state": "FL",
              "display_address": [
                  "1033 S Atlantic Ave",
                  "Cocoa Beach, FL 32931"
              ]
          },
          "phone": "+13217846564",
          "display_phone": "(321) 784-6564",
          "distance": 80225.07835458887
      },
      {
          "id": "RamlfnM3_0hFFIYReidcMw",
          "alias": "winter-haven-park-ponce-inlet",
          "name": "Winter Haven Park",
          "image_url": "https://s3-media2.fl.yelpcdn.com/bphoto/ML-I_fdrSs0o_e-_IwojOg/o.jpg",
          "is_closed": false,
          "url": "https://www.yelp.com/biz/winter-haven-park-ponce-inlet?adjust_creative=Yv4LCvsm1QJ6GtOp27fQ_w&utm_campaign=yelp_api_v3&utm_medium=api_v3_business_search&utm_source=Yv4LCvsm1QJ6GtOp27fQ_w",
          "review_count": 15,
          "categories": [
              {
                  "alias": "beaches",
                  "title": "Beaches"
              }
          ],
          "rating": 5.0,
          "coordinates": {
              "latitude": 29.105095,
              "longitude": -80.941109
          },
          "transactions": [],
          "location": {
              "address1": "4589 S Atlantic Ave",
              "address2": "",
              "address3": "",
              "city": "Ponce Inlet",
              "zip_code": "32127",
              "country": "US",
              "state": "FL",
              "display_address": [
                  "4589 S Atlantic Ave",
                  "Ponce Inlet, FL 32127"
              ]
          },
          "phone": "",
          "display_phone": "",
          "distance": 76114.26741155853
      },
      {
          "id": "5IqiN2kSMrCYUEZ-UPiK3g",
          "alias": "new-smyrna-beach-new-smyrna-beach-2",
          "name": "New Smyrna Beach",
          "image_url": "https://s3-media2.fl.yelpcdn.com/bphoto/byZO7QRzHmMSlM1b2tzjvw/o.jpg",
          "is_closed": false,
          "url": "https://www.yelp.com/biz/new-smyrna-beach-new-smyrna-beach-2?adjust_creative=Yv4LCvsm1QJ6GtOp27fQ_w&utm_campaign=yelp_api_v3&utm_medium=api_v3_business_search&utm_source=Yv4LCvsm1QJ6GtOp27fQ_w",
          "review_count": 23,
          "categories": [
              {
                  "alias": "beaches",
                  "title": "Beaches"
              }
          ],
          "rating": 4.5,
          "coordinates": {
              "latitude": 29.0253201,
              "longitude": -80.9285965
          },
          "transactions": [],
          "location": {
              "address1": "Washington St",
              "address2": "",
              "address3": "",
              "city": "New Smyrna Beach",
              "zip_code": "32168",
              "country": "US",
              "state": "FL",
              "display_address": [
                  "Washington St",
                  "New Smyrna Beach, FL 32168"
              ]
          },
          "phone": "",
          "display_phone": "",
          "distance": 69367.88359804133
      },
      {
          "id": "z92_B7q5lrCgSo4cjEBRvw",
          "alias": "canaveral-national-seashore-new-smyrna-beach-2",
          "name": "Canaveral National Seashore",
          "image_url": "https://s3-media1.fl.yelpcdn.com/bphoto/sge5ap5i8aSi4T-PNDMG8A/o.jpg",
          "is_closed": false,
          "url": "https://www.yelp.com/biz/canaveral-national-seashore-new-smyrna-beach-2?adjust_creative=Yv4LCvsm1QJ6GtOp27fQ_w&utm_campaign=yelp_api_v3&utm_medium=api_v3_business_search&utm_source=Yv4LCvsm1QJ6GtOp27fQ_w",
          "review_count": 15,
          "categories": [
              {
                  "alias": "beaches",
                  "title": "Beaches"
              }
          ],
          "rating": 4.5,
          "coordinates": {
              "latitude": 28.9382289,
              "longitude": -80.8312004
          },
          "transactions": [],
          "location": {
              "address1": "7175-7199 Turtlemound Rd",
              "address2": "",
              "address3": "",
              "city": "New Smyrna Beach",
              "zip_code": "32169",
              "country": "US",
              "state": "FL",
              "display_address": [
                  "7175-7199 Turtlemound Rd",
                  "New Smyrna Beach, FL 32169"
              ]
          },
          "phone": "",
          "display_phone": "",
          "distance": 69480.25100470363
      },
      {
          "id": "QFVbAtMOEYUlWDnka76OnQ",
          "alias": "playalinda-beach-orlando",
          "name": "Playalinda Beach",
          "image_url": "https://s3-media3.fl.yelpcdn.com/bphoto/ZFTVMt1CNSs1pom9_z7Dxw/o.jpg",
          "is_closed": false,
          "url": "https://www.yelp.com/biz/playalinda-beach-orlando?adjust_creative=Yv4LCvsm1QJ6GtOp27fQ_w&utm_campaign=yelp_api_v3&utm_medium=api_v3_business_search&utm_source=Yv4LCvsm1QJ6GtOp27fQ_w",
          "review_count": 17,
          "categories": [
              {
                  "alias": "beaches",
                  "title": "Beaches"
              }
          ],
          "rating": 4.5,
          "coordinates": {
              "latitude": 28.150312,
              "longitude": -81.617144
          },
          "transactions": [],
          "location": {
              "address1": "17 Olsen Rd",
              "address2": "",
              "address3": "Canaveral National Seashore",
              "city": "Orlando",
              "zip_code": "32815",
              "country": "US",
              "state": "FL",
              "display_address": [
                  "17 Olsen Rd",
                  "Canaveral National Seashore",
                  "Orlando, FL 32815"
              ]
          },
          "phone": "",
          "display_phone": "",
          "distance": 49027.19023360423
      },
      {
          "id": "TbVcgf1IrY31-TlUeyChVg",
          "alias": "canaveral-national-seashore-cape-canaveral",
          "name": "Canaveral National Seashore",
          "image_url": "https://s3-media3.fl.yelpcdn.com/bphoto/BYHhsODmGpEYSUiJPuVWbw/o.jpg",
          "is_closed": false,
          "url": "https://www.yelp.com/biz/canaveral-national-seashore-cape-canaveral?adjust_creative=Yv4LCvsm1QJ6GtOp27fQ_w&utm_campaign=yelp_api_v3&utm_medium=api_v3_business_search&utm_source=Yv4LCvsm1QJ6GtOp27fQ_w",
          "review_count": 14,
          "categories": [
              {
                  "alias": "beaches",
                  "title": "Beaches"
              }
          ],
          "rating": 4.5,
          "coordinates": {
              "latitude": 28.38459,
              "longitude": -80.60487
          },
          "transactions": [],
          "location": {
              "address1": "",
              "address2": "",
              "address3": "",
              "city": "Cape Canaveral",
              "zip_code": "32920",
              "country": "US",
              "state": "FL",
              "display_address": [
                  "Cape Canaveral, FL 32920"
              ]
          },
          "phone": "+13212671110",
          "display_phone": "(321) 267-1110",
          "distance": 77148.07679042805
      },
      {
          "id": "NaxJAzCUmcMvW1sRl16m5g",
          "alias": "daytona-beach-daytona-beach",
          "name": "Daytona Beach",
          "image_url": "https://s3-media3.fl.yelpcdn.com/bphoto/bE_584Bz-6TtBLQW-Ak2og/o.jpg",
          "is_closed": false,
          "url": "https://www.yelp.com/biz/daytona-beach-daytona-beach?adjust_creative=Yv4LCvsm1QJ6GtOp27fQ_w&utm_campaign=yelp_api_v3&utm_medium=api_v3_business_search&utm_source=Yv4LCvsm1QJ6GtOp27fQ_w",
          "review_count": 99,
          "categories": [
              {
                  "alias": "beaches",
                  "title": "Beaches"
              }
          ],
          "rating": 3.5,
          "coordinates": {
              "latitude": 29.20674,
              "longitude": -81.0198
          },
          "transactions": [],
          "location": {
              "address1": "301 S Ridgewood Ave",
              "address2": "",
              "address3": "",
              "city": "Daytona Beach",
              "zip_code": "32114",
              "country": "US",
              "state": "FL",
              "display_address": [
                  "301 S Ridgewood Ave",
                  "Daytona Beach, FL 32114"
              ]
          },
          "phone": "+13866718000",
          "display_phone": "(386) 671-8000",
          "distance": 82168.42539110186
      },
      {
          "id": "3lDvfIxnMcnVwQR4ceeiGA",
          "alias": "lighthouse-point-park-ponce-inlet",
          "name": "Lighthouse Point Park",
          "image_url": "https://s3-media1.fl.yelpcdn.com/bphoto/FGvaCY0jIQREaMn2t9qioQ/o.jpg",
          "is_closed": false,
          "url": "https://www.yelp.com/biz/lighthouse-point-park-ponce-inlet?adjust_creative=Yv4LCvsm1QJ6GtOp27fQ_w&utm_campaign=yelp_api_v3&utm_medium=api_v3_business_search&utm_source=Yv4LCvsm1QJ6GtOp27fQ_w",
          "review_count": 30,
          "categories": [
              {
                  "alias": "parks",
                  "title": "Parks"
              },
              {
                  "alias": "swimmingpools",
                  "title": "Swimming Pools"
              },
              {
                  "alias": "beaches",
                  "title": "Beaches"
              }
          ],
          "rating": 4.0,
          "coordinates": {
              "latitude": 29.0814730413425,
              "longitude": -80.9241522597534
          },
          "transactions": [],
          "location": {
              "address1": "5000 S Atlantic Ave",
              "address2": "",
              "address3": "",
              "city": "Ponce Inlet",
              "zip_code": "32127",
              "country": "US",
              "state": "FL",
              "display_address": [
                  "5000 S Atlantic Ave",
                  "Ponce Inlet, FL 32127"
              ]
          },
          "phone": "+13867567488",
          "display_phone": "(386) 756-7488",
          "distance": 74922.67866110527
      },
      {
          "id": "AZDMFAglfUcU7ZS1AbLfjw",
          "alias": "paradise-beach-and-park-indialantic",
          "name": "Paradise Beach & Park",
          "image_url": "https://s3-media2.fl.yelpcdn.com/bphoto/MOnpFDSPiz3ZjH0x4LgNzw/o.jpg",
          "is_closed": false,
          "url": "https://www.yelp.com/biz/paradise-beach-and-park-indialantic?adjust_creative=Yv4LCvsm1QJ6GtOp27fQ_w&utm_campaign=yelp_api_v3&utm_medium=api_v3_business_search&utm_source=Yv4LCvsm1QJ6GtOp27fQ_w",
          "review_count": 15,
          "categories": [
              {
                  "alias": "beaches",
                  "title": "Beaches"
              },
              {
                  "alias": "parks",
                  "title": "Parks"
              }
          ],
          "rating": 4.5,
          "coordinates": {
              "latitude": 28.122442,
              "longitude": -80.576051
          },
          "transactions": [],
          "location": {
              "address1": "113 Paradise Blvd",
              "address2": "",
              "address3": "",
              "city": "Indialantic",
              "zip_code": "32903",
              "country": "US",
              "state": "FL",
              "display_address": [
                  "113 Paradise Blvd",
                  "Indialantic, FL 32903"
              ]
          },
          "phone": "+13212554400",
          "display_phone": "(321) 255-4400",
          "distance": 91206.08630364868
      },
      {
          "id": "qGmo1pveNzWgCFUfkJEJFA",
          "alias": "indialantic-boardwalk-and-seashore-indialantic",
          "name": "Indialantic Boardwalk and Seashore",
          "image_url": "https://s3-media3.fl.yelpcdn.com/bphoto/HQtgjp5FJVsWQkko5OCxQw/o.jpg",
          "is_closed": false,
          "url": "https://www.yelp.com/biz/indialantic-boardwalk-and-seashore-indialantic?adjust_creative=Yv4LCvsm1QJ6GtOp27fQ_w&utm_campaign=yelp_api_v3&utm_medium=api_v3_business_search&utm_source=Yv4LCvsm1QJ6GtOp27fQ_w",
          "review_count": 17,
          "categories": [
              {
                  "alias": "beaches",
                  "title": "Beaches"
              }
          ],
          "rating": 4.0,
          "coordinates": {
              "latitude": 28.093229,
              "longitude": -80.56671
          },
          "transactions": [],
          "location": {
              "address1": "201 N Miramar Ave",
              "address2": "",
              "address3": "",
              "city": "Indialantic",
              "zip_code": "32903",
              "country": "US",
              "state": "FL",
              "display_address": [
                  "201 N Miramar Ave",
                  "Indialantic, FL 32903"
              ]
          },
          "phone": "",
          "display_phone": "",
          "distance": 93744.31378200717
      },
      {
          "id": "Yn4erA7f7fQZZRr8SiuUTg",
          "alias": "hightower-beach-park-satellite-beach",
          "name": "Hightower Beach Park",
          "image_url": "https://s3-media1.fl.yelpcdn.com/bphoto/blw7RjwDMSLZhqY4jrfiFA/o.jpg",
          "is_closed": false,
          "url": "https://www.yelp.com/biz/hightower-beach-park-satellite-beach?adjust_creative=Yv4LCvsm1QJ6GtOp27fQ_w&utm_campaign=yelp_api_v3&utm_medium=api_v3_business_search&utm_source=Yv4LCvsm1QJ6GtOp27fQ_w",
          "review_count": 12,
          "categories": [
              {
                  "alias": "parks",
                  "title": "Parks"
              },
              {
                  "alias": "beaches",
                  "title": "Beaches"
              }
          ],
          "rating": 4.5,
          "coordinates": {
              "latitude": 28.19439,
              "longitude": -80.594406
          },
          "transactions": [],
          "location": {
              "address1": "815 Hwy A1A",
              "address2": "",
              "address3": "",
              "city": "Satellite Beach",
              "zip_code": "32937",
              "country": "US",
              "state": "FL",
              "display_address": [
                  "815 Hwy A1A",
                  "Satellite Beach, FL 32937"
              ]
          },
          "phone": "",
          "display_phone": "",
          "distance": 85786.93793846901
      },
      {
          "id": "nfb2jxO5Sb8FlMF-o_vF7g",
          "alias": "new-smyrna-beach-27th-street-beach-access-new-smyrna-beach",
          "name": "New Smyrna Beach 27th Street Beach Access",
          "image_url": "https://s3-media3.fl.yelpcdn.com/bphoto/l-WHvklxrnm7l858Zt3Q0w/o.jpg",
          "is_closed": false,
          "url": "https://www.yelp.com/biz/new-smyrna-beach-27th-street-beach-access-new-smyrna-beach?adjust_creative=Yv4LCvsm1QJ6GtOp27fQ_w&utm_campaign=yelp_api_v3&utm_medium=api_v3_business_search&utm_source=Yv4LCvsm1QJ6GtOp27fQ_w",
          "review_count": 12,
          "categories": [
              {
                  "alias": "beaches",
                  "title": "Beaches"
              }
          ],
          "rating": 4.5,
          "coordinates": {
              "latitude": 29.009175313981,
              "longitude": -80.8779599073033
          },
          "transactions": [],
          "location": {
              "address1": "999 27th Ave",
              "address2": "",
              "address3": "",
              "city": "New Smyrna Beach",
              "zip_code": "32169",
              "country": "US",
              "state": "FL",
              "display_address": [
                  "999 27th Ave",
                  "New Smyrna Beach, FL 32169"
              ]
          },
          "phone": "",
          "display_phone": "",
          "distance": 71610.21670448982
      },
      {
          "id": "uiQby-O3QbgjN0SWFx9y_g",
          "alias": "ponce-inlet-town-of-ponce-inlet",
          "name": "Ponce Inlet Town of",
          "image_url": "https://s3-media1.fl.yelpcdn.com/bphoto/RC2vpWYFHermAKIgmzP-3A/o.jpg",
          "is_closed": false,
          "url": "https://www.yelp.com/biz/ponce-inlet-town-of-ponce-inlet?adjust_creative=Yv4LCvsm1QJ6GtOp27fQ_w&utm_campaign=yelp_api_v3&utm_medium=api_v3_business_search&utm_source=Yv4LCvsm1QJ6GtOp27fQ_w",
          "review_count": 7,
          "categories": [
              {
                  "alias": "beaches",
                  "title": "Beaches"
              }
          ],
          "rating": 5.0,
          "coordinates": {
              "latitude": 29.09859,
              "longitude": -80.940864
          },
          "transactions": [],
          "location": {
              "address1": "4680 S Peninsula Dr",
              "address2": "",
              "address3": "",
              "city": "Ponce Inlet",
              "zip_code": "32127",
              "country": "US",
              "state": "FL",
              "display_address": [
                  "4680 S Peninsula Dr",
                  "Ponce Inlet, FL 32127"
              ]
          },
          "phone": "",
          "display_phone": "",
          "distance": 75537.26163309289
      },
      {
          "id": "3LVIwtqw2-1vjDFZvNn0wA",
          "alias": "east-coast-paddle-new-smyrna-beach",
          "name": "East Coast Paddle",
          "image_url": "https://s3-media1.fl.yelpcdn.com/bphoto/dE6UXJSwgCpmpPthStV59Q/o.jpg",
          "is_closed": false,
          "url": "https://www.yelp.com/biz/east-coast-paddle-new-smyrna-beach?adjust_creative=Yv4LCvsm1QJ6GtOp27fQ_w&utm_campaign=yelp_api_v3&utm_medium=api_v3_business_search&utm_source=Yv4LCvsm1QJ6GtOp27fQ_w",
          "review_count": 6,
          "categories": [
              {
                  "alias": "fishing",
                  "title": "Fishing"
              },
              {
                  "alias": "beaches",
                  "title": "Beaches"
              },
              {
                  "alias": "paddleboarding",
                  "title": "Paddleboarding"
              }
          ],
          "rating": 5.0,
          "coordinates": {
              "latitude": 28.9468326568604,
              "longitude": -80.8381576538086
          },
          "transactions": [],
          "location": {
              "address1": "859 Pompano Ave",
              "address2": "",
              "address3": "",
              "city": "New Smyrna Beach",
              "zip_code": "32169",
              "country": "US",
              "state": "FL",
              "display_address": [
                  "859 Pompano Ave",
                  "New Smyrna Beach, FL 32169"
              ]
          },
          "phone": "+13864028585",
          "display_phone": "(386) 402-8585",
          "distance": 69613.13913757638
      },
      {
          "id": "LAg35qCnfTGmZ5xg2k4c4Q",
          "alias": "sun-splash-park-daytona-beach",
          "name": "Sun Splash Park",
          "image_url": "https://s3-media2.fl.yelpcdn.com/bphoto/iRCWfIRJ0SHlbY3VNL9c3Q/o.jpg",
          "is_closed": false,
          "url": "https://www.yelp.com/biz/sun-splash-park-daytona-beach?adjust_creative=Yv4LCvsm1QJ6GtOp27fQ_w&utm_campaign=yelp_api_v3&utm_medium=api_v3_business_search&utm_source=Yv4LCvsm1QJ6GtOp27fQ_w",
          "review_count": 17,
          "categories": [
              {
                  "alias": "beaches",
                  "title": "Beaches"
              }
          ],
          "rating": 4.0,
          "coordinates": {
              "latitude": 29.218468,
              "longitude": -81.003855
          },
          "transactions": [],
          "location": {
              "address1": "611 S Atlantic Ave",
              "address2": "",
              "address3": "",
              "city": "Daytona Beach",
              "zip_code": "32115",
              "country": "US",
              "state": "FL",
              "display_address": [
                  "611 S Atlantic Ave",
                  "Daytona Beach, FL 32115"
              ]
          },
          "phone": "+13867365953",
          "display_phone": "(386) 736-5953",
          "distance": 83996.05763315511
      },
      {
          "id": "MFenS48VQ99NfmhpaMM4aA",
          "alias": "alan-shepard-park-cocoa-beach",
          "name": "Alan Shepard Park",
          "image_url": "https://s3-media2.fl.yelpcdn.com/bphoto/OE7iAGdJPQadGzQ7WbQj-w/o.jpg",
          "is_closed": false,
          "url": "https://www.yelp.com/biz/alan-shepard-park-cocoa-beach?adjust_creative=Yv4LCvsm1QJ6GtOp27fQ_w&utm_campaign=yelp_api_v3&utm_medium=api_v3_business_search&utm_source=Yv4LCvsm1QJ6GtOp27fQ_w",
          "review_count": 9,
          "categories": [
              {
                  "alias": "beaches",
                  "title": "Beaches"
              },
              {
                  "alias": "parks",
                  "title": "Parks"
              }
          ],
          "rating": 4.0,
          "coordinates": {
              "latitude": 28.357952,
              "longitude": -80.605309
          },
          "transactions": [],
          "location": {
              "address1": "216-248 E Cocoa Beach Cswy",
              "address2": "",
              "address3": "",
              "city": "Cocoa Beach",
              "zip_code": "32931",
              "country": "US",
              "state": "FL",
              "display_address": [
                  "216-248 E Cocoa Beach Cswy",
                  "Cocoa Beach, FL 32931"
              ]
          },
          "phone": "",
          "display_phone": "",
          "distance": 78278.43107890763
      },
      {
          "id": "G3xsyAygFSSMN359yQNFGQ",
          "alias": "mary-mcleod-bethune-beach-park-new-smyrna-beach",
          "name": "Mary McLeod Bethune Beach Park",
          "image_url": "https://s3-media1.fl.yelpcdn.com/bphoto/9MZ5XBFhMAbMB6PtvgVvJw/o.jpg",
          "is_closed": false,
          "url": "https://www.yelp.com/biz/mary-mcleod-bethune-beach-park-new-smyrna-beach?adjust_creative=Yv4LCvsm1QJ6GtOp27fQ_w&utm_campaign=yelp_api_v3&utm_medium=api_v3_business_search&utm_source=Yv4LCvsm1QJ6GtOp27fQ_w",
          "review_count": 11,
          "categories": [
              {
                  "alias": "beaches",
                  "title": "Beaches"
              }
          ],
          "rating": 4.0,
          "coordinates": {
              "latitude": 28.9514896047509,
              "longitude": -80.8395362142439
          },
          "transactions": [],
          "location": {
              "address1": "6656 S Atlantic Ave",
              "address2": "",
              "address3": "",
              "city": "New Smyrna Beach",
              "zip_code": "32169",
              "country": "US",
              "state": "FL",
              "display_address": [
                  "6656 S Atlantic Ave",
                  "New Smyrna Beach, FL 32169"
              ]
          },
          "phone": "+13864233300",
          "display_phone": "(386) 423-3300",
          "distance": 69849.93833707125
      },
      {
          "id": "w9b3RcwGfHP-hvGFso-ADg",
          "alias": "bicentennial-beach-indian-harbour-beach",
          "name": "Bicentennial Beach",
          "image_url": "https://s3-media4.fl.yelpcdn.com/bphoto/EJNyLyy9Ezqzken41pk-9A/o.jpg",
          "is_closed": false,
          "url": "https://www.yelp.com/biz/bicentennial-beach-indian-harbour-beach?adjust_creative=Yv4LCvsm1QJ6GtOp27fQ_w&utm_campaign=yelp_api_v3&utm_medium=api_v3_business_search&utm_source=Yv4LCvsm1QJ6GtOp27fQ_w",
          "review_count": 4,
          "categories": [
              {
                  "alias": "beaches",
                  "title": "Beaches"
              }
          ],
          "rating": 4.5,
          "coordinates": {
              "latitude": 28.1534512,
              "longitude": -80.5843132
          },
          "transactions": [],
          "location": {
              "address1": "Ocean Dunes Dr",
              "address2": "",
              "address3": "",
              "city": "Indian Harbour Beach",
              "zip_code": "32937",
              "country": "US",
              "state": "FL",
              "display_address": [
                  "Ocean Dunes Dr",
                  "Indian Harbour Beach, FL 32937"
              ]
          },
          "phone": "+17024182946",
          "display_phone": "(702) 418-2946",
          "distance": 88787.8273569895
      }
  ],
  "total": 45,
  "region": {
      "center": {
          "longitude": -81.3792365,
          "latitude": 28.5383355
      }
  }
}